{
    "title_english": "Boralu Anena ",
    "title_sinhala": " බොරළු ඇනෙන",
    "lyrics": "බොරළු ඇනෙන පය රිදවන වෙහෙස මදක් නිවාගන්න\n                     \nඔබේ සතුටු මුහුණ අපට ටිකක් හොඳින් බලාගන්න\n \nමහත්වරුණි බදුලු ඔයෙන් කිරි කඳුලක් අපිත් ගන්න\n                        \nකාසි ඇතොත් මේ බෙලිමල් කඳුළු වතුර පොදක් බොන්න\nකැලේ ගිහින් නිදිවැරුවා\n                                  \nකැලේ ගිහින් නිදිවැරුවා කැපුන සඳුන් දන්ඩ දනී \nඒ සඳුනින් හිත තැවරූ සුවඳ පවා සිහින වැනී \nඅඳුරට දුක එකතු වෙලා\nඅඳුරට දුක එකතු වෙලා නින්ද බිඳුනු පැලට වදී\n                              \nඅපට නැතත් බදුලු ඔයට හෙටත් උදෑසනක් වඩී\nරෑන ගිරව් කටුසු කොබෙයි\n                                   \nරෑන ගිරව් කටුසු කොබෙයි උරග නාග සපුනි වනේ\nනුඹට වගේමයි අපටත් දුක් පීඩා විඩා දැනේ\n \nකඳු ඉස්මත්තෙන් පාවී\n                                \nකඳු ඉස්මත්තෙන් පාවී වැගිරෙන දුන්හිඳ හීනේ\n                                 \nපුංචි එවුන්ටයි ලස්සන කිරු ගරුඩෙන් කවිය වුනේ\n",
    "english_lyricst": " Ruchira Paranawitharana",
    "english_music": " Rohana Weerasingha",
    "english_artist": " Deepika Priyadarshani",
    "Genre": "නව පොප්",
    "sinhala_artist": "දීපිකා ප්‍රියදර්ශනී",
    "sinhala_lyricst": "රුචිරා පරණවිටාරණ",
    "sinhala_music": "රොහාන වීරසිංහ"
}