{
    "title_english": "Dasa Bimbara Mara- දස බිම්බර මාර",
    "title_sinhala": "",
    "lyrics": "දස බිම්බර මාර සෙනග තණ්හා රති රගා සමග\nපළවා හල වීතරාගි බුදුන් වඩිනවා\nහද වෙත බුදුන් වඩිනවා \n \t\t\t\t\nසංසාරේ තෙර දකින්න \nබලාපොරොත්තුවෙ ඔරුවෙන් \nගමන් වැඩිය අන්ගී රස \nබුදුන් වඩිනවා හද වෙත බුදුන් වඩිනවා\nසවණක් බුදු රැස් විහිදා\nකරුණාවේ මුදු බැල්මෙන් \nමුළු දියතෙහි සිසිල මවා\nබුදුන් වඩිනවා හද වෙත බුදුන් වඩිනවා\nමෙත් ගඟුලේ සෙනෙහෙ ගඟේ\nබුදු ගුණ ගී තරඟ නැගේ \nසාදු සාදු සාදු සාදු\nබුදුන් වඩිනවා හද වෙත බුදුන් වඩිනවා\n",
    "english_lyricst": " Somathilaka Jayamaha",
    "english_music": " Somathilaka Jayamaha",
    "english_artist": " Somathilaka Jayamaha",
    "Genre": "දේවානුභාවයෙන්",
    "sinhala_artist": "සෝමතිලක ජයමහා",
    "sinhala_lyricst": "සෝමතිලක ජයමහා",
    "sinhala_music": "සෝමතිලක ජයමහා"
}