{
    "title_english": "Adare Hithenawa  ",
    "title_sinhala": "  ආදරේ හිතෙනවා",
    "lyrics": "\t\t\t\t     \nආදරේ හිතෙනවා දැක්කම දෙවඟන වාගේ ලස්සනයි\n\t\t\t \t        \nපොඩ්ඩක් ඉන්න සුදෝ මං එනවා ළඟටම දැන් හොඳයි\n\t\t       \t  \nඔබ සොයා ඉගිළ එයි මා හදේ භෘංගයා \n\t\t                \nහැංඟුවේ ඇයි ප්‍රියේ මල් විලේ හංසයා\n\t      \t            \nහැංඟුවේ ඇයි ප්‍රියේ මල් විලේ හංසයා \n\t\t       \t  \nහැංඟුවේ නෑ කිසිත් ඇත්තමයි මා ඔබේ \n\t\t              \nමා සෙවූ මා පැතූ ආදරේ දැන් ලැබේ\n\t      \t           \nමා සෙවූ මා පැතූ ආදරේ දැන් ලැබේ\n",
    "english_lyricst": " Nihal Jayasingha",
    "english_music": " P.L.A.Somapala",
    "english_artist": [
        " Angelin Gunathilaka",
        " H.R.Jothipala"
    ],
    "Genre": [
        "යුගල",
        "චිත්‍රපට ගීත"
    ],
    "sinhala_artist": [
        "ඇන්ජලින් ගුණතිලක",
        "එච්.ආර්.ජෝතිපාල"
    ],
    "sinhala_lyricst": "නිහාල් ජයසිංහ",
    "sinhala_music": "පී.එල්.ඒ.සෝමපාල"
}