{
    "title_english": "Galana Gangaki ",
    "title_sinhala": " ගලන ගඟකි",
    "lyrics": "  —— ——— \n\t    \t   \t \nගලන ගඟකි ජීවිතේ දයාලූ ලෝකයේ\nමිහිර පතා ආදරේ \nමිහිර පතා ආදරේ\nලපළු නටයි ගංතෙරේ\n    \t    \nවැලිතල කිති කවන නටන \n           \t    \nපෙම් රළ වැළ ඉවුරු බඳින\nමිහිතලයට සුවය දැනෙන\n         \t   \nඋකුළු තලය බඳු නැලැවෙන\nපෙමට පෙම පුදා\nතුඩට තුඩු දිදී\nකුරුළු ගී නගයි\n\t    \nආදරේබැදීලා\n",
    "english_lyricst": " Chandrarathna Manawasingha",
    "english_music": " Pandith Amaradewa",
    "english_artist": [
        " Nanda Malani",
        " Narada Disasekara"
    ],
    "Genre": [
        "ක්ලැසික්",
        "චිත්‍රපට ගීත"
    ],
    "sinhala_artist": [
        "නන්ද මලනි",
        "නාරද දිසේකර"
    ],
    "sinhala_lyricst": "චන්ද්‍රරත්න මාවසිංහ",
    "sinhala_music": "පණ්ඩිත් අමරදේව"
}