{
    "title_english": "Adareta Kiyana Katha ",
    "title_sinhala": " ආදරේට කියන කතා",
    "lyrics": "\t           \t      \nආදරේට කියන කතා බොලඳ වුනාට\n\t \t                \nසාගරේක ගැඹුර දැනෙයි නොවෙද ඔයාට  \nතටු සිඳිලා වැලපෙනවා\n      \t    \nසිත බැඳිලා හිනැහෙනවා\n\t\t    \nමල් ඇතුරූ සුව යහනේ\nමල් අතුරා පවන් සැලු\nආදරවන්තයින් පෙලූ\n\t  \n බොලඳ කතා\nමල් ගොමුවේ තුරු සෙවනේ\n      \t    \nහමුවෙනවා වෙන්වෙනවා\n\t\t      \nඋයන් කොනේ අවන් හලේ\nඋයන් කොනේ හමුවෙනවා\nඅවන්හලේ වෙන්වෙනවා\n\t  \nබොලඳ කතා\n",
    "english_lyricst": " Clarence Wijewardena",
    "english_music": " Clarence Wijewardena",
    "english_artist": " Clarence Wijewardena",
    "Genre": "පැරණි පොප්ස්",
    "sinhala_artist": "ක්ලැරන්ස් විජේවර්ධන",
    "sinhala_lyricst": "ක්ලැරන්ස් විජේවර්ධන",
    "sinhala_music": "ක්ලැරන්ස් විජේවර්ධන"
}