{
    "title_english": "Issara Kale Patan ",
    "title_sinhala": " ඉස්සර කාලේ පටන්",
    "lyrics": "ඉස්සර කාලේ පටන් අපේ අය\nරස ගී සිංදු ගොතන් ගැයූ හැටි\nමතකයි තාම හොඳින්\nවයාල වයලින් බැංජො රබන්\nන න න න නා නා න න න න නා නා\nන න න න නා නා න න න න නා නා\nස රි ග ම ප ධ නි  හරියට දැනගෙන\nරාග තාල හෑම අකුරට රැකගෙන\nතබ්ල සර්පිනාව අරගෙන\nකීව සිංදු ඇත තවමත් නොමැරෙන\nකීව සිංදු තවමත් ඇත නොමැරන\nආගම දහමට නිසි ගරු කෙරුනා\nයහ ගුණ මග නිසි පෙන්නා දුන්නා\nමසුරන් වටිනා පදවැල් ගෙතුනා\nඒ ගී රස තවමත් පවතින්නා\nකාලෙන් කාලෙට තාල වෙනස්ලු\nසංගීතය දැන් හරි දියුනුයුලු\nකෙරුවත් සමහරු ඉඳහිට විහුළු\nදන්න අයට බොරු කරන්න බැරිලූ \n",
    "english_lyricst": " Siha Shakthi",
    "english_music": " Siha Shakthi",
    "english_artist": " Siha Shakthi",
    "Genre": [
        "කණ්ඩායම් ගීත",
        "ඉල්ලීම"
    ],
    "sinhala_artist": "සිහා ශක්ති",
    "sinhala_lyricst": "සිහා ශක්ති",
    "sinhala_music": "සිහා ශක්ති"
}