{
    "title_english": "Kohe Ho Numba ",
    "title_sinhala": " කොහේ හෝ නුඹ",
    "lyrics": "කොහේ හෝ නුඹ නතර වි \nකාට හෝ ජීවිතය දී\nතුටින් නම් මට ඒ ඇති\nමගේ නොවුනට කම් නැතී නුඹ\nමගේ නොවුනට කම් නැතී\nඋන්න දා අපි අපේ වී නුඹ\nදුන්නු සෙනෙහස අරුමැති\nලෝභ නෑ හිත අහිමි දා අද\nමමත් දැන් මට හිමි නැතී\nනුඹ ළඟත් මතකය ඇතී\nනමුදු අපි වෙන් වී ඇතී\nඑපා රිදවුම් ගන්න දිවියට\nඅපිට හිමි ජීවිත ඇතී\n",
    "english_lyricst": " Shamila Hussain",
    "english_music": " Dharshana Wickramathunga",
    "english_artist": " Karunaratna Divulgane",
    "Genre": "නව පොප්",
    "sinhala_artist": "කරුණාරත්න ඩිවුල්ගනේ",
    "sinhala_lyricst": "ෂමිලා හුසේන්",
    "sinhala_music": "දර්ශන වික්‍රමතුංග"
}