{
    "title_english": "Aradhana ",
    "title_sinhala": " ආරාධනා",
    "lyrics": " ………………\n                 \t                 \t\t \nආරාධනා…… ආරාධනා\nජීවිතයේ තනි මංසල අතරමං වෙලා\nහුදෙකලාව සුසුම් හෙලන හදවත සනහා\nඅතීතයේ ගිලිහී ගිය සතුට රැගෙන යලි වඩින්න\nආරාධනා ආරාධනා\n\t\t\t                \nනෙලූ සුපෙම් කැටයම් හද පවුරැ තලාවේ  \nමැකී ගියාදෝ……………කාලයේ වෙරළේ\nජීවිතයේ දිගු ගමනින් අනාත වූ දා  \nසෙනේහයේ සත් පියුමන් යළිදු පිපේවා\nආරාධනා ආරාධනා\n\t\t\t              \nඑදා සිඟිති කිරි සුවඳින් යුග දිවි අරණේ  \nඔබේ උණුසුමේ…………………යළිදු උපන්නෙම්\nබිඳුණු එවන් රජ දහනින් සමු ගෙන යනදා \nඔබේ නුවන් පහනින් යළි එළිය ලැබේවා\nආරාධනා ආරාධනා\n",
    "english_lyricst": null,
    "english_music": null,
    "english_artist": " W.D.Amaradewa",
    "sinhala_artist": "ඩබ්ලිව්.ඩී අමරදේව"
}